labelme/__init__.py
labelme/__main__.py
labelme/_label_file.py
labelme/app.py
labelme/shape.py
labelme/testing.py
labelme/_automation/__init__.py
labelme/_automation/bbox_from_text.py
labelme/_automation/polygon_from_mask.py
labelme/cli/__init__.py
labelme/cli/draw_json.py
labelme/cli/draw_label_png.py
labelme/cli/export_json.py
labelme/cli/on_docker.py
labelme/config/__init__.py
labelme/config/default_config.yaml
labelme/icons/ai-mask.svg
labelme/icons/ai-polygon.svg
labelme/icons/arrow-fat-left.svg
labelme/icons/arrow-fat-right.svg
labelme/icons/arrow-u-up-left.svg
labelme/icons/brightness-contrast.svg
labelme/icons/circle.svg
labelme/icons/circles-four.svg
labelme/icons/copy.svg
labelme/icons/eye.svg
labelme/icons/file-x.svg
labelme/icons/floppy-disk.svg
labelme/icons/folder-open.svg
labelme/icons/folders.svg
labelme/icons/frame-arrows-horizontal.svg
labelme/icons/frame-corners.svg
labelme/icons/icon-128.png
labelme/icons/icon-16.png
labelme/icons/icon-256.png
labelme/icons/icon-32.png
labelme/icons/icon-48.png
labelme/icons/icon-64.png
labelme/icons/icon.ico
labelme/icons/image-square.svg
labelme/icons/line-segment.svg
labelme/icons/line-segments.svg
labelme/icons/magnifying-glass-minus.svg
labelme/icons/magnifying-glass-plus.svg
labelme/icons/note-pencil.svg
labelme/icons/paint-bucket.svg
labelme/icons/polygon.svg
labelme/icons/question.svg
labelme/icons/rectangle.svg
labelme/icons/trash.svg
labelme/icons/x-circle.svg
labelme/translate/zh_CN.qm
labelme/translate/zh_CN.ts
labelme/utils/__init__.py
labelme/utils/_io.py
labelme/utils/image.py
labelme/utils/qt.py
labelme/utils/shape.py
labelme/widgets/__init__.py
labelme/widgets/_status.py
labelme/widgets/ai_prompt_widget.py
labelme/widgets/brightness_contrast_dialog.py
labelme/widgets/canvas.py
labelme/widgets/download.py
labelme/widgets/file_dialog_preview.py
labelme/widgets/image_grid_viewer.py
labelme/widgets/label_dialog.py
labelme/widgets/label_list_widget.py
labelme/widgets/tool_bar.py
xj_labelme-1.0.7.dist-info/METADATA
xj_labelme-1.0.7.dist-info/WHEEL
xj_labelme-1.0.7.dist-info/entry_points.txt
xj_labelme-1.0.7.dist-info/licenses/LICENSE
xj_labelme-1.0.7.dist-info/RECORD
